weather_mcp_server/__init__.py
weather_mcp_server/server.py
weather_mcp_server/tools/__init__.py
weather_mcp_server/tools/weather.py
weather_mcp_server-1.0.1.dist-info/METADATA
weather_mcp_server-1.0.1.dist-info/WHEEL
weather_mcp_server-1.0.1.dist-info/entry_points.txt
weather_mcp_server-1.0.1.dist-info/licenses/LICENSE
weather_mcp_server-1.0.1.dist-info/RECORD
