Metadata-Version: 2.4
Name: weather-mcp-server
Version: 1.0.1
Summary: A weather MCP server built with FastMCP
Project-URL: Homepage, https://github.com/qianyan/weather-mcp-server
Project-URL: Repository, https://github.com/qianyan/weather-mcp-server.git
Author-email: qianyan <qianyan.lambda@gmail.com>
License: MIT
License-File: LICENSE
Keywords: claude,fastmcp,mcp,weather
Classifier: Development Status :: 4 - Beta
Classifier: Intended Audience :: Developers
Classifier: License :: OSI Approved :: MIT License
Classifier: Programming Language :: Python :: 3.13
Requires-Python: >=3.13
Requires-Dist: fastmcp>=0.4.1
Requires-Dist: pydantic==2.11.1
Requires-Dist: python-dotenv==1.1.0
Requires-Dist: requests==2.32.3
Provides-Extra: dev
Requires-Dist: build; extra == 'dev'
Requires-Dist: ruff>=0.11.2; extra == 'dev'
Requires-Dist: tomli-w>=1.0.0; extra == 'dev'
Requires-Dist: tomli>=2.0.1; extra == 'dev'
Requires-Dist: twine; extra == 'dev'
